[
  {
    "symbol": "CHF=X",
    "pair_name": "USD/CHF",
    "signal": "BUY",
    "confidence": 66,
    "current_price": 0.81309,
    "take_profit": 0.81404,
    "stop_loss": "Aucun",
    "tp_pct": 0.117,
    "sl_pct": 0.0,
    "rsi": 65.5,
    "rsi_status": "Neutre ⚖️",
    "macd_trend": "Haussier 📈",
    "ema_trend": "Haussier 📈",
    "bb_position": "Proche Borne Haute ⚠️",
    "atr": 0.00038,
    "forecast_dir": "TFM:SELL/CHO:BUY/MOI:HOLD/LLA:BUY/GRA:BUY",
    "forecast_4h": 0.81303,
    "forecast_24h": 0.81303,
    "fisher": 1.58,
    "fisher_status": "Neutre",
    "timestamp": 1784730960.4622066,
    "timeframe": "5m"
  },
  {
    "symbol": "EURCHF=X",
    "pair_name": "EUR/CHF",
    "signal": "BUY",
    "confidence": 62,
    "current_price": 0.92788,
    "take_profit": 0.92946,
    "stop_loss": "Aucun",
    "tp_pct": 0.17,
    "sl_pct": 0.0,
    "rsi": 77.8,
    "rsi_status": "Surachat 🔴",
    "macd_trend": "Haussier 📈",
    "ema_trend": "Haussier 📈",
    "bb_position": "Proche Borne Haute ⚠️",
    "atr": 0.00063,
    "forecast_dir": "TFM:HOLD/CHO:BUY/MOI:BUY/LLA:SELL/GRA:BUY",
    "forecast_4h": 0.92786,
    "forecast_24h": 0.92786,
    "fisher": 2.21,
    "fisher_status": "Neutre",
    "timestamp": 1784730960.8138268,
    "timeframe": "5m"
  },
  {
    "symbol": "EURCHF=X",
    "pair_name": "EUR/CHF",
    "signal": "BUY",
    "confidence": 62,
    "current_price": 0.92786,
    "take_profit": 0.92972,
    "stop_loss": "Aucun",
    "tp_pct": 0.2,
    "sl_pct": 0.0,
    "rsi": 72.6,
    "rsi_status": "Surachat 🔴",
    "macd_trend": "Haussier 📈",
    "ema_trend": "Haussier 📈",
    "bb_position": "Proche Borne Haute ⚠️",
    "atr": 0.00074,
    "forecast_dir": "TFM:HOLD/CHO:BUY/MOI:BUY/LLA:SELL/GRA:BUY",
    "forecast_4h": 0.92788,
    "forecast_24h": 0.92788,
    "fisher": 1.9,
    "fisher_status": "Neutre",
    "timestamp": 1784730961.1656072,
    "timeframe": "15m"
  },
  {
    "symbol": "AUDCHF=X",
    "pair_name": "AUD/CHF",
    "signal": "BUY",
    "confidence": 56,
    "current_price": 0.56868,
    "take_profit": 0.57101,
    "stop_loss": "Aucun",
    "tp_pct": 0.41,
    "sl_pct": 0.0,
    "rsi": 63.5,
    "rsi_status": "Neutre ⚖️",
    "macd_trend": "Haussier 📈",
    "ema_trend": "Baissier 📉",
    "bb_position": "Proche Borne Haute ⚠️",
    "atr": 0.00093,
    "forecast_dir": "TFM:BUY/CHO:SELL/MOI:BUY/LLA:SELL/GRA:BUY",
    "forecast_4h": 0.56874,
    "forecast_24h": 0.56874,
    "fisher": 1.53,
    "fisher_status": "Neutre",
    "timestamp": 1784730961.6200364,
    "timeframe": "15m"
  },
  {
    "symbol": "EURCHF=X",
    "pair_name": "EUR/CHF",
    "signal": "BUY",
    "confidence": 75,
    "current_price": 0.92786,
    "take_profit": 0.93081,
    "stop_loss": "Aucun",
    "tp_pct": 0.318,
    "sl_pct": 0.0,
    "rsi": 67.4,
    "rsi_status": "Neutre ⚖️",
    "macd_trend": "Haussier 📈",
    "ema_trend": "Haussier 📈",
    "bb_position": "Proche Borne Haute ⚠️",
    "atr": 0.00084,
    "forecast_dir": "TFM:BUY/CHO:BUY/MOI:BUY/LLA:SELL/GRA:BUY",
    "forecast_4h": 0.92792,
    "forecast_24h": 0.92792,
    "fisher": 1.79,
    "fisher_status": "Neutre",
    "timestamp": 1784730962.0074809,
    "timeframe": "30m"
  }
]