{
  "last_update": "2026-07-22T21:22:24.384239+00:00",
  "signals": [
    {
      "pair_name": "GBP/CHF",
      "signal": "BUY",
      "current_price": 1.08867,
      "take_profit": 1.09073,
      "stop_loss": "Aucun",
      "confidence": 72,
      "rsi": 37.4,
      "macd_trend": "Baissier 📉",
      "forecast_dir": "TFM:BUY/CHO:BUY/MOI:BUY/LLA:SELL/GRA:BUY",
      "timeframe": "5m",
      "macro_info": {
        "base": "GBP",
        "quote": "CHF",
        "rate_base": 3.75,
        "rate_quote": 0.0,
        "rate_diff": 3.75,
        "inf_base": 2.6,
        "inf_quote": 0.5,
        "gdp_base": 0.6,
        "gdp_quote": 0.4
      }
    },
    {
      "pair_name": "EUR/USD",
      "signal": "SELL",
      "current_price": 1.14116,
      "take_profit": 1.14016,
      "stop_loss": "Aucun",
      "confidence": 71,
      "rsi": 44.3,
      "macd_trend": "Baissier 📉",
      "forecast_dir": "TFM:HOLD/CHO:SELL/MOI:SELL/LLA:SELL/GRA:SELL",
      "timeframe": "15m",
      "macro_info": {
        "base": "EUR",
        "quote": "USD",
        "rate_base": 2.4,
        "rate_quote": 3.75,
        "rate_diff": -1.35,
        "inf_base": 2.8,
        "inf_quote": 3.5,
        "gdp_base": 0.0,
        "gdp_quote": 2.1
      }
    },
    {
      "pair_name": "EUR/USD",
      "signal": "SELL",
      "current_price": 1.14116,
      "take_profit": 1.14079,
      "stop_loss": "Aucun",
      "confidence": 69,
      "rsi": 39.4,
      "macd_trend": "Baissier 📉",
      "forecast_dir": "TFM:HOLD/CHO:SELL/MOI:HOLD/LLA:SELL/GRA:SELL",
      "timeframe": "5m",
      "macro_info": {
        "base": "EUR",
        "quote": "USD",
        "rate_base": 2.4,
        "rate_quote": 3.75,
        "rate_diff": -1.35,
        "inf_base": 2.8,
        "inf_quote": 3.5,
        "gdp_base": 0.0,
        "gdp_quote": 2.1
      }
    },
    {
      "pair_name": "AUD/CAD",
      "signal": "BUY",
      "current_price": 0.98404,
      "take_profit": 0.98888,
      "stop_loss": "Aucun",
      "confidence": 68,
      "rsi": 34.5,
      "macd_trend": "Baissier 📉",
      "forecast_dir": "TFM:BUY/CHO:BUY/MOI:BUY/LLA:SELL/GRA:BUY",
      "timeframe": "30m",
      "macro_info": {
        "base": "AUD",
        "quote": "CAD",
        "rate_base": 4.35,
        "rate_quote": 2.25,
        "rate_diff": 2.0999999999999996,
        "inf_base": 4.0,
        "inf_quote": 2.8,
        "gdp_base": 0.3,
        "gdp_quote": 0.0
      }
    },
    {
      "pair_name": "AUD/CHF",
      "signal": "BUY",
      "current_price": 0.56909,
      "take_profit": 0.57313,
      "stop_loss": "Aucun",
      "confidence": 68,
      "rsi": 65.2,
      "macd_trend": "Haussier 📈",
      "forecast_dir": "TFM:BUY/CHO:BUY/MOI:BUY/LLA:SELL/GRA:BUY",
      "timeframe": "30m",
      "macro_info": {
        "base": "AUD",
        "quote": "CHF",
        "rate_base": 4.35,
        "rate_quote": 0.0,
        "rate_diff": 4.35,
        "inf_base": 4.0,
        "inf_quote": 0.5,
        "gdp_base": 0.3,
        "gdp_quote": 0.4
      }
    },
    {
      "pair_name": "USD/TRY",
      "signal": "BUY",
      "current_price": 47.1945,
      "take_profit": 47.35645,
      "stop_loss": "Aucun",
      "confidence": 66,
      "rsi": 43.9,
      "macd_trend": "Baissier 📉",
      "forecast_dir": "TFM:BUY/CHO:BUY/MOI:BUY/LLA:BUY/GRA:HOLD",
      "timeframe": "30m",
      "macro_info": null
    },
    {
      "pair_name": "AUD/CAD",
      "signal": "BUY",
      "current_price": 0.984,
      "take_profit": 0.98701,
      "stop_loss": "Aucun",
      "confidence": 65,
      "rsi": 29.5,
      "macd_trend": "Baissier 📉",
      "forecast_dir": "TFM:SELL/CHO:BUY/MOI:BUY/LLA:SELL/GRA:BUY",
      "timeframe": "15m",
      "macro_info": {
        "base": "AUD",
        "quote": "CAD",
        "rate_base": 4.35,
        "rate_quote": 2.25,
        "rate_diff": 2.0999999999999996,
        "inf_base": 4.0,
        "inf_quote": 2.8,
        "gdp_base": 0.3,
        "gdp_quote": 0.0
      }
    },
    {
      "pair_name": "USD/JPY",
      "signal": "BUY",
      "current_price": 163.091,
      "take_profit": 163.19107,
      "stop_loss": "Aucun",
      "confidence": 64,
      "rsi": 40.8,
      "macd_trend": "Baissier 📉",
      "forecast_dir": "TFM:BUY/CHO:BUY/MOI:BUY/LLA:BUY/GRA:HOLD",
      "timeframe": "5m",
      "macro_info": null
    },
    {
      "pair_name": "GBP/CAD",
      "signal": "SELL",
      "current_price": 1.88321,
      "take_profit": 1.88087,
      "stop_loss": "Aucun",
      "confidence": 64,
      "rsi": 44.7,
      "macd_trend": "Baissier 📉",
      "forecast_dir": "TFM:BUY/CHO:SELL/MOI:HOLD/LLA:SELL/GRA:SELL",
      "timeframe": "5m",
      "macro_info": {
        "base": "GBP",
        "quote": "CAD",
        "rate_base": 3.75,
        "rate_quote": 2.25,
        "rate_diff": 1.5,
        "inf_base": 2.6,
        "inf_quote": 2.8,
        "gdp_base": 0.6,
        "gdp_quote": 0.0
      }
    },
    {
      "pair_name": "AUD/CHF",
      "signal": "BUY",
      "current_price": 0.56909,
      "take_profit": 0.57148,
      "stop_loss": "Aucun",
      "confidence": 64,
      "rsi": 49.5,
      "macd_trend": "Haussier 📈",
      "forecast_dir": "TFM:SELL/CHO:BUY/MOI:BUY/LLA:SELL/GRA:BUY",
      "timeframe": "30m",
      "macro_info": {
        "base": "AUD",
        "quote": "CHF",
        "rate_base": 4.35,
        "rate_quote": 0.0,
        "rate_diff": 4.35,
        "inf_base": 4.0,
        "inf_quote": 0.5,
        "gdp_base": 0.3,
        "gdp_quote": 0.4
      }
    }
  ]
}